{"commit":{"sha":"a7ac71b97899f1fac87a70c87a2b98e46877918b","date":"2017-06-09T10:28:12Z"},"benchmarks":{"jld-day15-parser":[{"patch":"","name":"jld-day15-parser","runs":[{"name":"jld-day15-parser","passes":[{"name":"parsing","time":0.001,"mem":53},{"name":"recursion limit","time":0.0,"mem":53},{"name":"crate injection","time":0.0,"mem":53},{"name":"plugin loading","time":0.0,"mem":53},{"name":"plugin registration","time":0.0,"mem":53},{"name":"expansion","time":0.076,"mem":86},{"name":"maybe building test harness","time":0.0,"mem":86},{"name":"maybe creating a macro crate","time":0.0,"mem":86},{"name":"checking for inline asm in case the target doesn't support it","time":0.0,"mem":86},{"name":"early lint checks","time":0.0,"mem":86},{"name":"AST validation","time":0.0,"mem":86},{"name":"name resolution","time":0.004,"mem":88},{"name":"complete gated feature checking","time":0.0,"mem":88},{"name":"lowering ast -> hir","time":0.0,"mem":88},{"name":"indexing hir","time":0.0,"mem":88},{"name":"attribute checking","time":0.0,"mem":88},{"name":"language item collection","time":0.0,"mem":88},{"name":"lifetime resolution","time":0.0,"mem":88},{"name":"looking for entry point","time":0.0,"mem":88},{"name":"looking for plugin registrar","time":0.0,"mem":88},{"name":"loop checking","time":0.0,"mem":88},{"name":"static item recursion checking","time":0.0,"mem":88},{"name":"compute_incremental_hashes_map","time":0.005000000000000001,"mem":92},{"name":"load_dep_graph","time":0.0,"mem":92},{"name":"stability index","time":0.0,"mem":92},{"name":"stability checking","time":0.001,"mem":92},{"name":"type collecting","time":0.004999999999999999,"mem":92},{"name":"impl wf inference","time":0.0,"mem":92},{"name":"coherence checking","time":0.001,"mem":92},{"name":"variance testing","time":0.0,"mem":92},{"name":"wf checking","time":0.010000000000000002,"mem":97},{"name":"item-types checking","time":0.0095,"mem":99},{"name":"item-bodies checking","time":0.075,"mem":111},{"name":"const checking","time":0.003,"mem":111},{"name":"privacy checking","time":0.0,"mem":111},{"name":"intrinsic checking","time":0.0,"mem":111},{"name":"effect checking","time":0.0,"mem":111},{"name":"match checking","time":0.0,"mem":111},{"name":"liveness checking","time":0.0,"mem":111},{"name":"borrow checking","time":0.015,"mem":111},{"name":"reachability checking","time":0.0,"mem":111},{"name":"death checking","time":0.0,"mem":111},{"name":"unused lib feature checking","time":0.0,"mem":111},{"name":"lint checking","time":0.009000000000000001,"mem":111},{"name":"resolving dependency formats","time":0.0,"mem":111},{"name":"translation","time":2.2119999999999999,"mem":149},{"name":"assert dep graph","time":0.0,"mem":149},{"name":"serialize dep graph","time":0.0,"mem":149},{"name":"LLVM passes","time":1.6965,"mem":153},{"name":"serialize work products","time":0.0,"mem":153},{"name":"linking","time":0.41500000000000006,"mem":142}]}]}],"syntex-0.42.2":[{"patch":"@000-base","name":"syntex-0.42.2","runs":[{"name":"syntex-0.42.2@000-base","passes":[{"name":"parsing","time":0.3075,"mem":74},{"name":"recursion limit","time":0.0,"mem":74},{"name":"crate injection","time":0.0,"mem":74},{"name":"plugin loading","time":0.0,"mem":74},{"name":"plugin registration","time":0.0,"mem":74},{"name":"expansion","time":1.238,"mem":162},{"name":"maybe building test harness","time":0.0,"mem":162},{"name":"maybe creating a macro crate","time":0.0155,"mem":162},{"name":"checking for inline asm in case the target doesn't support it","time":0.0,"mem":162},{"name":"early lint checks","time":0.0945,"mem":162},{"name":"AST validation","time":0.016,"mem":162},{"name":"name resolution","time":1.1855,"mem":373},{"name":"complete gated feature checking","time":0.057499999999999999,"mem":373},{"name":"lowering ast -> hir","time":0.23299999999999999,"mem":418},{"name":"indexing hir","time":0.07250000000000001,"mem":216},{"name":"attribute checking","time":0.018000000000000003,"mem":216},{"name":"language item collection","time":0.009,"mem":196},{"name":"lifetime resolution","time":0.037500000000000009,"mem":196},{"name":"looking for entry point","time":0.0,"mem":196},{"name":"looking for plugin registrar","time":0.0,"mem":196},{"name":"loop checking","time":0.028999999999999999,"mem":196},{"name":"static item recursion checking","time":0.0024999999999999998,"mem":196},{"name":"compute_incremental_hashes_map","time":0.7464999999999999,"mem":198},{"name":"load_dep_graph","time":0.0,"mem":198},{"name":"stability index","time":0.028,"mem":198},{"name":"stability checking","time":0.051500000000000007,"mem":199},{"name":"type collecting","time":0.136,"mem":209},{"name":"impl wf inference","time":0.007,"mem":209},{"name":"coherence checking","time":0.0875,"mem":216},{"name":"variance testing","time":0.001,"mem":216},{"name":"wf checking","time":0.6054999999999999,"mem":230},{"name":"item-types checking","time":0.404,"mem":234},{"name":"item-bodies checking","time":10.9695,"mem":286},{"name":"const checking","time":0.841,"mem":309},{"name":"privacy checking","time":0.164,"mem":309},{"name":"intrinsic checking","time":0.0335,"mem":309},{"name":"effect checking","time":0.029500000000000003,"mem":309},{"name":"match checking","time":0.1545,"mem":309},{"name":"liveness checking","time":0.1115,"mem":322},{"name":"borrow checking","time":3.441,"mem":393},{"name":"reachability checking","time":0.031,"mem":393},{"name":"death checking","time":0.0755,"mem":393},{"name":"unused lib feature checking","time":0.0,"mem":393},{"name":"lint checking","time":0.8855,"mem":393},{"name":"resolving dependency formats","time":0.0,"mem":393},{"name":"translation","time":18.9195,"mem":746},{"name":"assert dep graph","time":0.0,"mem":746},{"name":"serialize dep graph","time":0.0,"mem":746},{"name":"LLVM passes","time":48.022999999999999,"mem":506},{"name":"serialize work products","time":0.0,"mem":506},{"name":"linking","time":0.977,"mem":212}]}]},{"patch":"@010-incr","name":"syntex-0.42.2","runs":[{"name":"syntex-0.42.2@010-incr","passes":[{"name":"parsing","time":0.3185,"mem":74},{"name":"recursion limit","time":0.0,"mem":74},{"name":"crate injection","time":0.0,"mem":74},{"name":"plugin loading","time":0.0,"mem":74},{"name":"plugin registration","time":0.0,"mem":74},{"name":"expansion","time":1.2955,"mem":168},{"name":"maybe building test harness","time":0.0,"mem":168},{"name":"maybe creating a macro crate","time":0.016,"mem":168},{"name":"checking for inline asm in case the target doesn't support it","time":0.0,"mem":168},{"name":"early lint checks","time":0.088,"mem":168},{"name":"AST validation","time":0.018500000000000004,"mem":168},{"name":"name resolution","time":1.366,"mem":381},{"name":"complete gated feature checking","time":0.062,"mem":381},{"name":"lowering ast -> hir","time":0.2565,"mem":421},{"name":"indexing hir","time":0.076,"mem":219},{"name":"attribute checking","time":0.016,"mem":219},{"name":"language item collection","time":0.0029999999999999998,"mem":199},{"name":"lifetime resolution","time":0.045,"mem":199},{"name":"looking for entry point","time":0.0,"mem":199},{"name":"looking for plugin registrar","time":0.0,"mem":199},{"name":"loop checking","time":0.019,"mem":199},{"name":"static item recursion checking","time":0.0085,"mem":199},{"name":"compute_incremental_hashes_map","time":0.877,"mem":211},{"name":"load_dep_graph","time":0.0,"mem":211},{"name":"stability index","time":0.0245,"mem":211},{"name":"stability checking","time":0.0605,"mem":212},{"name":"type collecting","time":0.186,"mem":229},{"name":"impl wf inference","time":0.0045,"mem":232},{"name":"coherence checking","time":0.1345,"mem":240},{"name":"variance testing","time":0.005000000000000001,"mem":240},{"name":"wf checking","time":0.8280000000000001,"mem":264},{"name":"item-types checking","time":0.4325,"mem":267},{"name":"item-bodies checking","time":12.2875,"mem":329},{"name":"const checking","time":1.0295,"mem":353},{"name":"privacy checking","time":0.2375,"mem":353},{"name":"intrinsic checking","time":0.0345,"mem":353},{"name":"effect checking","time":0.036500000000000008,"mem":353},{"name":"match checking","time":0.151,"mem":353},{"name":"liveness checking","time":0.1205,"mem":371},{"name":"borrow checking","time":4.013999999999999,"mem":451},{"name":"reachability checking","time":0.0305,"mem":452},{"name":"death checking","time":0.096,"mem":452},{"name":"unused lib feature checking","time":0.0,"mem":452},{"name":"lint checking","time":0.9359999999999999,"mem":453},{"name":"resolving dependency formats","time":0.0,"mem":453},{"name":"translation","time":37.73650000000001,"mem":1097},{"name":"assert dep graph","time":0.0,"mem":1097},{"name":"serialize dep graph","time":2.6784999999999998,"mem":1108},{"name":"LLVM passes","time":82.70400000000001,"mem":933},{"name":"serialize work products","time":0.0,"mem":933},{"name":"linking","time":2.279,"mem":283}]}]},{"patch":"@020-clean","name":"syntex-0.42.2","runs":[{"name":"syntex-0.42.2@020-clean","passes":[]}]}],"html5ever-2016-08-25":[{"patch":"","name":"html5ever-2016-08-25","runs":[{"name":"html5ever-2016-08-25","passes":[{"name":"parsing","time":0.07250000000000001,"mem":58},{"name":"recursion limit","time":0.0,"mem":58},{"name":"crate injection","time":0.0,"mem":58},{"name":"plugin loading","time":0.0,"mem":58},{"name":"plugin registration","time":0.0,"mem":58},{"name":"expansion","time":1.5855000000000002,"mem":123},{"name":"maybe building test harness","time":0.0,"mem":123},{"name":"maybe creating a macro crate","time":0.001,"mem":123},{"name":"checking for inline asm in case the target doesn't support it","time":0.0,"mem":123},{"name":"early lint checks","time":0.03,"mem":123},{"name":"AST validation","time":0.008,"mem":123},{"name":"name resolution","time":0.155,"mem":142},{"name":"complete gated feature checking","time":0.004999999999999999,"mem":142},{"name":"lowering ast -> hir","time":0.05,"mem":157},{"name":"indexing hir","time":0.0185,"mem":142},{"name":"attribute checking","time":0.002,"mem":142},{"name":"language item collection","time":0.0,"mem":127},{"name":"lifetime resolution","time":0.004,"mem":127},{"name":"looking for entry point","time":0.0,"mem":127},{"name":"looking for plugin registrar","time":0.0,"mem":127},{"name":"loop checking","time":0.0015,"mem":127},{"name":"static item recursion checking","time":0.0065,"mem":127},{"name":"compute_incremental_hashes_map","time":0.0555,"mem":129},{"name":"load_dep_graph","time":0.0,"mem":129},{"name":"stability index","time":0.002,"mem":129},{"name":"stability checking","time":0.003,"mem":129},{"name":"type collecting","time":0.036,"mem":138},{"name":"impl wf inference","time":0.0,"mem":138},{"name":"coherence checking","time":0.054000000000000009,"mem":145},{"name":"variance testing","time":0.0,"mem":145},{"name":"wf checking","time":0.1285,"mem":151},{"name":"item-types checking","time":1.129,"mem":160},{"name":"item-bodies checking","time":1.311,"mem":174},{"name":"const checking","time":0.201,"mem":176},{"name":"privacy checking","time":0.0175,"mem":176},{"name":"intrinsic checking","time":0.002,"mem":176},{"name":"effect checking","time":0.006,"mem":176},{"name":"match checking","time":0.043,"mem":176},{"name":"liveness checking","time":0.0325,"mem":171},{"name":"borrow checking","time":0.898,"mem":193},{"name":"reachability checking","time":0.006999999999999999,"mem":193},{"name":"death checking","time":0.011000000000000001,"mem":193},{"name":"unused lib feature checking","time":0.0,"mem":193},{"name":"lint checking","time":0.276,"mem":195},{"name":"resolving dependency formats","time":0.0,"mem":195},{"name":"translation","time":2.2805,"mem":240},{"name":"assert dep graph","time":0.0,"mem":240},{"name":"serialize dep graph","time":0.0,"mem":240},{"name":"LLVM passes","time":2.2355,"mem":181},{"name":"serialize work products","time":0.0,"mem":181},{"name":"linking","time":0.07050000000000001,"mem":166}]}]}],"issue-32062-equality-relations-complexity":[{"patch":"","name":"issue-32062-equality-relations-complexity","runs":[{"name":"issue-32062-equality-relations-complexity","passes":[{"name":"parsing","time":0.005,"mem":53},{"name":"recursion limit","time":0.0,"mem":53},{"name":"crate injection","time":0.0,"mem":53},{"name":"plugin loading","time":0.0,"mem":53},{"name":"plugin registration","time":0.0,"mem":53},{"name":"expansion","time":0.064,"mem":82},{"name":"maybe building test harness","time":0.0,"mem":82},{"name":"maybe creating a macro crate","time":0.0,"mem":82},{"name":"checking for inline asm in case the target doesn't support it","time":0.0,"mem":82},{"name":"early lint checks","time":0.0,"mem":82},{"name":"AST validation","time":0.0,"mem":82},{"name":"name resolution","time":0.001,"mem":82},{"name":"complete gated feature checking","time":0.0,"mem":82},{"name":"lowering ast -> hir","time":0.0,"mem":82},{"name":"indexing hir","time":0.0,"mem":82},{"name":"attribute checking","time":0.0,"mem":82},{"name":"language item collection","time":0.0,"mem":82},{"name":"lifetime resolution","time":0.0,"mem":82},{"name":"looking for entry point","time":0.0,"mem":82},{"name":"looking for plugin registrar","time":0.0,"mem":82},{"name":"loop checking","time":0.0,"mem":82},{"name":"static item recursion checking","time":0.0,"mem":82},{"name":"compute_incremental_hashes_map","time":0.0,"mem":86},{"name":"load_dep_graph","time":0.0,"mem":86},{"name":"stability index","time":0.0,"mem":86},{"name":"stability checking","time":0.001,"mem":86},{"name":"type collecting","time":0.001,"mem":86},{"name":"impl wf inference","time":0.0,"mem":86},{"name":"coherence checking","time":0.0,"mem":86},{"name":"variance testing","time":0.0,"mem":86},{"name":"wf checking","time":0.018000000000000003,"mem":91},{"name":"item-types checking","time":0.006999999999999999,"mem":93},{"name":"item-bodies checking","time":0.0465,"mem":99},{"name":"const checking","time":0.005000000000000001,"mem":99},{"name":"privacy checking","time":0.0,"mem":99},{"name":"intrinsic checking","time":0.0,"mem":99},{"name":"effect checking","time":0.0,"mem":99},{"name":"match checking","time":0.0,"mem":99},{"name":"liveness checking","time":0.0,"mem":99},{"name":"borrow checking","time":0.034,"mem":99},{"name":"reachability checking","time":0.0,"mem":99},{"name":"death checking","time":0.0,"mem":99},{"name":"unused lib feature checking","time":0.0,"mem":99},{"name":"lint checking","time":0.001,"mem":99},{"name":"resolving dependency formats","time":0.0,"mem":99},{"name":"translation","time":0.3385,"mem":118},{"name":"assert dep graph","time":0.0,"mem":118},{"name":"serialize dep graph","time":0.0,"mem":118},{"name":"LLVM passes","time":0.0605,"mem":122},{"name":"serialize work products","time":0.0,"mem":122},{"name":"linking","time":0.3595,"mem":126}]}]}],"tuple-stress":[{"patch":"","name":"tuple-stress","runs":[{"name":"tuple-stress","passes":[{"name":"parsing","time":1.3965,"mem":139},{"name":"recursion limit","time":0.0,"mem":139},{"name":"crate injection","time":0.0,"mem":139},{"name":"plugin loading","time":0.0,"mem":139},{"name":"plugin registration","time":0.0,"mem":139},{"name":"expansion","time":0.2825,"mem":160},{"name":"maybe building test harness","time":0.0,"mem":160},{"name":"maybe creating a macro crate","time":0.01,"mem":160},{"name":"checking for inline asm in case the target doesn't support it","time":0.0,"mem":160},{"name":"early lint checks","time":0.137,"mem":160},{"name":"AST validation","time":0.017,"mem":160},{"name":"name resolution","time":0.024,"mem":161},{"name":"complete gated feature checking","time":0.019,"mem":161},{"name":"lowering ast -> hir","time":0.119,"mem":210},{"name":"indexing hir","time":0.0955,"mem":235},{"name":"attribute checking","time":0.011,"mem":235},{"name":"language item collection","time":0.0,"mem":156},{"name":"lifetime resolution","time":0.017,"mem":156},{"name":"looking for entry point","time":0.0,"mem":156},{"name":"looking for plugin registrar","time":0.0,"mem":156},{"name":"loop checking","time":0.008,"mem":156},{"name":"static item recursion checking","time":0.0025,"mem":156},{"name":"compute_incremental_hashes_map","time":0.4405,"mem":156},{"name":"load_dep_graph","time":0.0,"mem":156},{"name":"stability index","time":0.007,"mem":156},{"name":"stability checking","time":0.0024999999999999998,"mem":156},{"name":"type collecting","time":0.013,"mem":160},{"name":"impl wf inference","time":0.0,"mem":160},{"name":"coherence checking","time":0.0,"mem":160},{"name":"variance testing","time":0.0,"mem":160},{"name":"wf checking","time":0.139,"mem":185},{"name":"item-types checking","time":3.2005,"mem":222},{"name":"item-bodies checking","time":0.02,"mem":235},{"name":"const checking","time":0.79,"mem":249},{"name":"privacy checking","time":0.022,"mem":249},{"name":"intrinsic checking","time":0.015,"mem":249},{"name":"effect checking","time":0.004999999999999999,"mem":249},{"name":"match checking","time":0.011,"mem":249},{"name":"liveness checking","time":0.003,"mem":249},{"name":"borrow checking","time":2.3205,"mem":289},{"name":"reachability checking","time":0.0,"mem":289},{"name":"death checking","time":0.0155,"mem":289},{"name":"unused lib feature checking","time":0.0,"mem":289},{"name":"lint checking","time":1.0545,"mem":289},{"name":"resolving dependency formats","time":0.004,"mem":289},{"name":"translation","time":1.478,"mem":335},{"name":"assert dep graph","time":0.0,"mem":335},{"name":"serialize dep graph","time":0.0,"mem":335},{"name":"LLVM passes","time":1.0135,"mem":173},{"name":"serialize work products","time":0.0,"mem":173},{"name":"linking","time":0.3575,"mem":139}]}]}],"issue-32278-big-array-of-strings":[{"patch":"","name":"issue-32278-big-array-of-strings","runs":[{"name":"issue-32278-big-array-of-strings","passes":[{"name":"parsing","time":0.3605,"mem":69},{"name":"recursion limit","time":0.0,"mem":69},{"name":"crate injection","time":0.0,"mem":69},{"name":"plugin loading","time":0.0,"mem":69},{"name":"plugin registration","time":0.0,"mem":69},{"name":"expansion","time":0.086,"mem":98},{"name":"maybe building test harness","time":0.0,"mem":98},{"name":"maybe creating a macro crate","time":0.0,"mem":98},{"name":"checking for inline asm in case the target doesn't support it","time":0.0,"mem":98},{"name":"early lint checks","time":0.0195,"mem":98},{"name":"AST validation","time":0.0005,"mem":98},{"name":"name resolution","time":0.008,"mem":98},{"name":"complete gated feature checking","time":0.001,"mem":98},{"name":"lowering ast -> hir","time":0.010499999999999999,"mem":108},{"name":"indexing hir","time":0.01,"mem":115},{"name":"attribute checking","time":0.001,"mem":115},{"name":"language item collection","time":0.0,"mem":105},{"name":"lifetime resolution","time":0.001,"mem":105},{"name":"looking for entry point","time":0.0,"mem":105},{"name":"looking for plugin registrar","time":0.0,"mem":105},{"name":"loop checking","time":0.0,"mem":105},{"name":"static item recursion checking","time":0.004,"mem":105},{"name":"compute_incremental_hashes_map","time":0.0885,"mem":105},{"name":"load_dep_graph","time":0.0,"mem":105},{"name":"stability index","time":0.0005,"mem":105},{"name":"stability checking","time":0.0,"mem":105},{"name":"type collecting","time":0.0085,"mem":109},{"name":"impl wf inference","time":0.0,"mem":109},{"name":"coherence checking","time":0.0,"mem":109},{"name":"variance testing","time":0.0,"mem":109},{"name":"wf checking","time":0.0155,"mem":115},{"name":"item-types checking","time":2.8855,"mem":124},{"name":"item-bodies checking","time":0.0,"mem":124},{"name":"const checking","time":0.0935,"mem":132},{"name":"privacy checking","time":0.001,"mem":132},{"name":"intrinsic checking","time":0.0009999999999999996,"mem":132},{"name":"effect checking","time":0.0,"mem":132},{"name":"match checking","time":0.0,"mem":132},{"name":"liveness checking","time":0.0,"mem":132},{"name":"borrow checking","time":0.28200000000000005,"mem":135},{"name":"reachability checking","time":0.0,"mem":135},{"name":"death checking","time":0.001,"mem":135},{"name":"unused lib feature checking","time":0.0,"mem":135},{"name":"lint checking","time":0.16,"mem":135},{"name":"resolving dependency formats","time":0.0,"mem":135},{"name":"translation","time":0.5175000000000001,"mem":165},{"name":"assert dep graph","time":0.0,"mem":165},{"name":"serialize dep graph","time":0.0,"mem":165},{"name":"LLVM passes","time":0.719,"mem":132},{"name":"serialize work products","time":0.0,"mem":132},{"name":"linking","time":0.4995,"mem":122}]}]}],"regex.0.1.30":[{"patch":"","name":"regex.0.1.30","runs":[{"name":"regex.0.1.30","passes":[{"name":"parsing","time":0.1615,"mem":66},{"name":"recursion limit","time":0.0,"mem":66},{"name":"crate injection","time":0.0,"mem":66},{"name":"plugin loading","time":0.0,"mem":66},{"name":"plugin registration","time":0.0,"mem":66},{"name":"expansion","time":0.132,"mem":96},{"name":"maybe building test harness","time":0.0,"mem":96},{"name":"maybe creating a macro crate","time":0.0,"mem":96},{"name":"checking for inline asm in case the target doesn't support it","time":0.0,"mem":96},{"name":"early lint checks","time":0.017,"mem":96},{"name":"AST validation","time":0.0005,"mem":96},{"name":"name resolution","time":0.055499999999999997,"mem":108},{"name":"complete gated feature checking","time":0.009,"mem":108},{"name":"lowering ast -> hir","time":0.025500000000000003,"mem":117},{"name":"indexing hir","time":0.004,"mem":111},{"name":"attribute checking","time":0.001,"mem":111},{"name":"language item collection","time":0.0,"mem":104},{"name":"lifetime resolution","time":0.0075,"mem":104},{"name":"looking for entry point","time":0.0,"mem":104},{"name":"looking for plugin registrar","time":0.0,"mem":104},{"name":"loop checking","time":0.0,"mem":104},{"name":"static item recursion checking","time":0.0,"mem":104},{"name":"compute_incremental_hashes_map","time":0.057499999999999999,"mem":104},{"name":"load_dep_graph","time":0.0,"mem":104},{"name":"stability index","time":0.001,"mem":104},{"name":"stability checking","time":0.006,"mem":106},{"name":"type collecting","time":0.0155,"mem":115},{"name":"impl wf inference","time":0.0,"mem":115},{"name":"coherence checking","time":0.0545,"mem":123},{"name":"variance testing","time":0.0,"mem":123},{"name":"wf checking","time":0.0395,"mem":125},{"name":"item-types checking","time":0.3105,"mem":132},{"name":"item-bodies checking","time":0.4625,"mem":136},{"name":"const checking","time":0.1535,"mem":145},{"name":"privacy checking","time":0.004,"mem":145},{"name":"intrinsic checking","time":0.005,"mem":145},{"name":"effect checking","time":0.005000000000000001,"mem":145},{"name":"match checking","time":0.003,"mem":145},{"name":"liveness checking","time":0.002,"mem":145},{"name":"borrow checking","time":0.241,"mem":149},{"name":"reachability checking","time":0.004,"mem":149},{"name":"death checking","time":0.0025,"mem":149},{"name":"unused lib feature checking","time":0.0,"mem":149},{"name":"lint checking","time":0.1385,"mem":149},{"name":"resolving dependency formats","time":0.0,"mem":149},{"name":"translation","time":1.8119999999999999,"mem":205},{"name":"assert dep graph","time":0.0,"mem":205},{"name":"serialize dep graph","time":0.0,"mem":205},{"name":"LLVM passes","time":3.6109999999999999,"mem":178},{"name":"serialize work products","time":0.0,"mem":178},{"name":"linking","time":0.10400000000000001,"mem":154}]}]}],"helloworld":[{"patch":"","name":"helloworld","runs":[{"name":"helloworld","passes":[{"name":"parsing","time":0.0,"mem":51},{"name":"recursion limit","time":0.0,"mem":51},{"name":"crate injection","time":0.0,"mem":51},{"name":"plugin loading","time":0.0,"mem":51},{"name":"plugin registration","time":0.0,"mem":51},{"name":"expansion","time":0.061,"mem":79},{"name":"maybe building test harness","time":0.0,"mem":79},{"name":"maybe creating a macro crate","time":0.0,"mem":79},{"name":"checking for inline asm in case the target doesn't support it","time":0.0,"mem":79},{"name":"early lint checks","time":0.0,"mem":79},{"name":"AST validation","time":0.0,"mem":79},{"name":"name resolution","time":0.001,"mem":79},{"name":"complete gated feature checking","time":0.0,"mem":79},{"name":"lowering ast -> hir","time":0.0,"mem":84},{"name":"indexing hir","time":0.0,"mem":84},{"name":"attribute checking","time":0.0,"mem":84},{"name":"language item collection","time":0.0,"mem":84},{"name":"lifetime resolution","time":0.0,"mem":84},{"name":"looking for entry point","time":0.0,"mem":84},{"name":"looking for plugin registrar","time":0.0,"mem":84},{"name":"loop checking","time":0.0,"mem":84},{"name":"static item recursion checking","time":0.0,"mem":84},{"name":"compute_incremental_hashes_map","time":0.0,"mem":84},{"name":"load_dep_graph","time":0.0,"mem":84},{"name":"stability index","time":0.0,"mem":84},{"name":"stability checking","time":0.0,"mem":84},{"name":"type collecting","time":0.0,"mem":84},{"name":"impl wf inference","time":0.0,"mem":84},{"name":"coherence checking","time":0.0,"mem":84},{"name":"variance testing","time":0.0,"mem":84},{"name":"wf checking","time":0.0,"mem":84},{"name":"item-types checking","time":0.002,"mem":86},{"name":"item-bodies checking","time":0.011,"mem":90},{"name":"const checking","time":0.004,"mem":96},{"name":"privacy checking","time":0.0,"mem":96},{"name":"intrinsic checking","time":0.0,"mem":96},{"name":"effect checking","time":0.0,"mem":96},{"name":"match checking","time":0.0,"mem":96},{"name":"liveness checking","time":0.0,"mem":96},{"name":"borrow checking","time":0.001,"mem":96},{"name":"reachability checking","time":0.0,"mem":96},{"name":"death checking","time":0.0,"mem":96},{"name":"unused lib feature checking","time":0.0,"mem":96},{"name":"lint checking","time":0.0,"mem":96},{"name":"resolving dependency formats","time":0.0,"mem":96},{"name":"translation","time":0.1605,"mem":115},{"name":"assert dep graph","time":0.0,"mem":115},{"name":"serialize dep graph","time":0.0,"mem":115},{"name":"LLVM passes","time":0.019000000000000004,"mem":119},{"name":"serialize work products","time":0.0,"mem":119},{"name":"linking","time":0.351,"mem":119}]}]}],"rust-encoding-0.3.0":[{"patch":"","name":"rust-encoding-0.3.0","runs":[{"name":"rust-encoding-0.3.0","passes":[{"name":"parsing","time":0.052500000000000008,"mem":56},{"name":"recursion limit","time":0.0,"mem":56},{"name":"crate injection","time":0.0,"mem":56},{"name":"plugin loading","time":0.0,"mem":56},{"name":"plugin registration","time":0.0,"mem":56},{"name":"expansion","time":0.152,"mem":91},{"name":"maybe building test harness","time":0.0,"mem":91},{"name":"maybe creating a macro crate","time":0.0,"mem":91},{"name":"checking for inline asm in case the target doesn't support it","time":0.0,"mem":91},{"name":"early lint checks","time":0.006999999999999999,"mem":91},{"name":"AST validation","time":0.0,"mem":91},{"name":"name resolution","time":0.0225,"mem":93},{"name":"complete gated feature checking","time":0.003,"mem":93},{"name":"lowering ast -> hir","time":0.0155,"mem":99},{"name":"indexing hir","time":0.002,"mem":99},{"name":"attribute checking","time":0.004,"mem":99},{"name":"language item collection","time":0.0,"mem":99},{"name":"lifetime resolution","time":0.0009999999999999996,"mem":99},{"name":"looking for entry point","time":0.0,"mem":99},{"name":"looking for plugin registrar","time":0.0,"mem":99},{"name":"loop checking","time":0.0,"mem":99},{"name":"static item recursion checking","time":0.0,"mem":99},{"name":"compute_incremental_hashes_map","time":0.0335,"mem":99},{"name":"load_dep_graph","time":0.0,"mem":99},{"name":"stability index","time":0.0005,"mem":99},{"name":"stability checking","time":0.002,"mem":99},{"name":"type collecting","time":0.0275,"mem":111},{"name":"impl wf inference","time":0.0,"mem":111},{"name":"coherence checking","time":0.0325,"mem":118},{"name":"variance testing","time":0.0,"mem":118},{"name":"wf checking","time":0.0655,"mem":118},{"name":"item-types checking","time":0.044,"mem":120},{"name":"item-bodies checking","time":0.46699999999999999,"mem":126},{"name":"const checking","time":0.05,"mem":126},{"name":"privacy checking","time":0.006999999999999999,"mem":126},{"name":"intrinsic checking","time":0.001,"mem":126},{"name":"effect checking","time":0.0005,"mem":126},{"name":"match checking","time":0.014,"mem":126},{"name":"liveness checking","time":0.002,"mem":126},{"name":"borrow checking","time":0.16999999999999999,"mem":136},{"name":"reachability checking","time":0.0005,"mem":136},{"name":"death checking","time":0.002,"mem":136},{"name":"unused lib feature checking","time":0.0,"mem":136},{"name":"lint checking","time":0.0665,"mem":136},{"name":"resolving dependency formats","time":0.0,"mem":136},{"name":"translation","time":1.464,"mem":202},{"name":"assert dep graph","time":0.0,"mem":202},{"name":"serialize dep graph","time":0.0,"mem":202},{"name":"LLVM passes","time":3.333,"mem":178},{"name":"serialize work products","time":0.0,"mem":178},{"name":"linking","time":0.109,"mem":151}]}]}],"piston-image-0.10.3":[{"patch":"","name":"piston-image-0.10.3","runs":[{"name":"piston-image-0.10.3","passes":[{"name":"parsing","time":0.131,"mem":62},{"name":"recursion limit","time":0.0,"mem":62},{"name":"crate injection","time":0.0,"mem":62},{"name":"plugin loading","time":0.0,"mem":62},{"name":"plugin registration","time":0.0,"mem":62},{"name":"expansion","time":0.3225,"mem":112},{"name":"maybe building test harness","time":0.0,"mem":112},{"name":"maybe creating a macro crate","time":0.001,"mem":112},{"name":"checking for inline asm in case the target doesn't support it","time":0.0,"mem":112},{"name":"early lint checks","time":0.020499999999999999,"mem":112},{"name":"AST validation","time":0.005000000000000001,"mem":112},{"name":"name resolution","time":0.29000000000000006,"mem":167},{"name":"complete gated feature checking","time":0.017,"mem":167},{"name":"lowering ast -> hir","time":0.0505,"mem":181},{"name":"indexing hir","time":0.019000000000000004,"mem":129},{"name":"attribute checking","time":0.002,"mem":129},{"name":"language item collection","time":0.005,"mem":128},{"name":"lifetime resolution","time":0.004999999999999999,"mem":128},{"name":"looking for entry point","time":0.0,"mem":128},{"name":"looking for plugin registrar","time":0.0,"mem":128},{"name":"loop checking","time":0.001,"mem":128},{"name":"static item recursion checking","time":0.0065,"mem":128},{"name":"compute_incremental_hashes_map","time":0.125,"mem":129},{"name":"load_dep_graph","time":0.0,"mem":129},{"name":"stability index","time":0.0025,"mem":129},{"name":"stability checking","time":0.0055,"mem":130},{"name":"type collecting","time":0.058499999999999999,"mem":140},{"name":"impl wf inference","time":0.001,"mem":140},{"name":"coherence checking","time":0.07150000000000001,"mem":149},{"name":"variance testing","time":0.004,"mem":149},{"name":"wf checking","time":0.2865,"mem":155},{"name":"item-types checking","time":0.151,"mem":156},{"name":"item-bodies checking","time":2.7535,"mem":169},{"name":"const checking","time":0.2095,"mem":174},{"name":"privacy checking","time":0.024,"mem":174},{"name":"intrinsic checking","time":0.002,"mem":174},{"name":"effect checking","time":0.006,"mem":174},{"name":"match checking","time":0.0275,"mem":174},{"name":"liveness checking","time":0.022,"mem":174},{"name":"borrow checking","time":0.769,"mem":192},{"name":"reachability checking","time":0.0045000000000000009,"mem":192},{"name":"death checking","time":0.023,"mem":192},{"name":"unused lib feature checking","time":0.0,"mem":192},{"name":"lint checking","time":0.2615,"mem":192},{"name":"resolving dependency formats","time":0.0,"mem":192},{"name":"translation","time":9.2965,"mem":366},{"name":"assert dep graph","time":0.0,"mem":366},{"name":"serialize dep graph","time":0.0,"mem":366},{"name":"LLVM passes","time":19.334,"mem":301},{"name":"serialize work products","time":0.0,"mem":301},{"name":"linking","time":0.3745,"mem":188}]}]}],"regex-0.1.80":[{"patch":"@010-baseline","name":"regex-0.1.80","runs":[{"name":"regex-0.1.80@010-baseline","passes":[{"name":"parsing","time":0.107,"mem":60},{"name":"recursion limit","time":0.0,"mem":60},{"name":"crate injection","time":0.0,"mem":60},{"name":"plugin loading","time":0.0,"mem":60},{"name":"plugin registration","time":0.0,"mem":60},{"name":"expansion","time":0.225,"mem":99},{"name":"maybe building test harness","time":0.0,"mem":99},{"name":"maybe creating a macro crate","time":0.0009999999999999996,"mem":99},{"name":"checking for inline asm in case the target doesn't support it","time":0.0,"mem":99},{"name":"early lint checks","time":0.018,"mem":99},{"name":"AST validation","time":0.001,"mem":99},{"name":"name resolution","time":0.0755,"mem":116},{"name":"complete gated feature checking","time":0.033,"mem":116},{"name":"lowering ast -> hir","time":0.03,"mem":122},{"name":"indexing hir","time":0.012,"mem":115},{"name":"attribute checking","time":0.001,"mem":115},{"name":"language item collection","time":0.0,"mem":112},{"name":"lifetime resolution","time":0.0065,"mem":112},{"name":"looking for entry point","time":0.0,"mem":112},{"name":"looking for plugin registrar","time":0.0,"mem":112},{"name":"loop checking","time":0.005000000000000001,"mem":112},{"name":"static item recursion checking","time":0.0,"mem":112},{"name":"compute_incremental_hashes_map","time":0.066,"mem":112},{"name":"load_dep_graph","time":0.0,"mem":112},{"name":"stability index","time":0.001,"mem":112},{"name":"stability checking","time":0.007,"mem":115},{"name":"type collecting","time":0.03,"mem":123},{"name":"impl wf inference","time":0.0,"mem":123},{"name":"coherence checking","time":0.064,"mem":130},{"name":"variance testing","time":0.0,"mem":130},{"name":"wf checking","time":0.125,"mem":135},{"name":"item-types checking","time":0.0885,"mem":137},{"name":"item-bodies checking","time":1.1735,"mem":147},{"name":"const checking","time":0.1225,"mem":149},{"name":"privacy checking","time":0.017,"mem":149},{"name":"intrinsic checking","time":0.005500000000000001,"mem":149},{"name":"effect checking","time":0.0015,"mem":149},{"name":"match checking","time":0.0155,"mem":149},{"name":"liveness checking","time":0.0085,"mem":149},{"name":"borrow checking","time":0.44,"mem":162},{"name":"reachability checking","time":0.001,"mem":162},{"name":"death checking","time":0.013,"mem":162},{"name":"unused lib feature checking","time":0.0,"mem":162},{"name":"lint checking","time":0.156,"mem":162},{"name":"resolving dependency formats","time":0.0,"mem":162},{"name":"translation","time":3.6595,"mem":251},{"name":"assert dep graph","time":0.0,"mem":251},{"name":"serialize dep graph","time":0.0,"mem":251},{"name":"LLVM passes","time":13.400500000000001,"mem":250},{"name":"serialize work products","time":0.0,"mem":250},{"name":"linking","time":0.34299999999999999,"mem":163}]}]},{"patch":"@020-incr-from-scratch","name":"regex-0.1.80","runs":[{"name":"regex-0.1.80@020-incr-from-scratch","passes":[{"name":"parsing","time":0.1015,"mem":59},{"name":"recursion limit","time":0.0,"mem":59},{"name":"crate injection","time":0.0,"mem":59},{"name":"plugin loading","time":0.0,"mem":59},{"name":"plugin registration","time":0.0,"mem":59},{"name":"expansion","time":0.2385,"mem":102},{"name":"maybe building test harness","time":0.0,"mem":102},{"name":"maybe creating a macro crate","time":0.001,"mem":102},{"name":"checking for inline asm in case the target doesn't support it","time":0.0,"mem":102},{"name":"early lint checks","time":0.014,"mem":102},{"name":"AST validation","time":0.001,"mem":102},{"name":"name resolution","time":0.092,"mem":119},{"name":"complete gated feature checking","time":0.028,"mem":121},{"name":"lowering ast -> hir","time":0.034,"mem":127},{"name":"indexing hir","time":0.0045000000000000009,"mem":119},{"name":"attribute checking","time":0.001,"mem":119},{"name":"language item collection","time":0.006,"mem":116},{"name":"lifetime resolution","time":0.003,"mem":116},{"name":"looking for entry point","time":0.0,"mem":116},{"name":"looking for plugin registrar","time":0.0,"mem":116},{"name":"loop checking","time":0.001,"mem":116},{"name":"static item recursion checking","time":0.0,"mem":116},{"name":"compute_incremental_hashes_map","time":0.083,"mem":122},{"name":"load_dep_graph","time":0.0,"mem":122},{"name":"stability index","time":0.006,"mem":122},{"name":"stability checking","time":0.008,"mem":123},{"name":"type collecting","time":0.043,"mem":133},{"name":"impl wf inference","time":0.001,"mem":133},{"name":"coherence checking","time":0.10300000000000001,"mem":146},{"name":"variance testing","time":0.0,"mem":146},{"name":"wf checking","time":0.167,"mem":154},{"name":"item-types checking","time":0.10200000000000001,"mem":156},{"name":"item-bodies checking","time":1.3435000000000002,"mem":164},{"name":"const checking","time":0.1465,"mem":168},{"name":"privacy checking","time":0.023,"mem":168},{"name":"intrinsic checking","time":0.005500000000000001,"mem":168},{"name":"effect checking","time":0.0015,"mem":168},{"name":"match checking","time":0.019,"mem":168},{"name":"liveness checking","time":0.009000000000000001,"mem":168},{"name":"borrow checking","time":0.498,"mem":181},{"name":"reachability checking","time":0.002,"mem":181},{"name":"death checking","time":0.014,"mem":181},{"name":"unused lib feature checking","time":0.0,"mem":181},{"name":"lint checking","time":0.1725,"mem":181},{"name":"resolving dependency formats","time":0.0,"mem":181},{"name":"translation","time":6.662,"mem":319},{"name":"assert dep graph","time":0.0,"mem":319},{"name":"serialize dep graph","time":0.4915,"mem":340},{"name":"LLVM passes","time":19.395,"mem":344},{"name":"serialize work products","time":0.0,"mem":344},{"name":"linking","time":0.5565,"mem":191}]}]},{"patch":"@030-compile_one","name":"regex-0.1.80","runs":[{"name":"regex-0.1.80@030-compile_one","passes":[{"name":"parsing","time":0.10200000000000001,"mem":60},{"name":"recursion limit","time":0.0,"mem":60},{"name":"crate injection","time":0.0,"mem":60},{"name":"plugin loading","time":0.0,"mem":60},{"name":"plugin registration","time":0.0,"mem":60},{"name":"expansion","time":0.2405,"mem":103},{"name":"maybe building test harness","time":0.0,"mem":103},{"name":"maybe creating a macro crate","time":0.0009999999999999996,"mem":103},{"name":"checking for inline asm in case the target doesn't support it","time":0.0,"mem":103},{"name":"early lint checks","time":0.006,"mem":103},{"name":"AST validation","time":0.007,"mem":103},{"name":"name resolution","time":0.0925,"mem":119},{"name":"complete gated feature checking","time":0.0295,"mem":121},{"name":"lowering ast -> hir","time":0.0325,"mem":128},{"name":"indexing hir","time":0.0085,"mem":119},{"name":"attribute checking","time":0.001,"mem":119},{"name":"language item collection","time":0.0,"mem":116},{"name":"lifetime resolution","time":0.0095,"mem":116},{"name":"looking for entry point","time":0.0,"mem":116},{"name":"looking for plugin registrar","time":0.0,"mem":116},{"name":"loop checking","time":0.005000000000000001,"mem":116},{"name":"static item recursion checking","time":0.0,"mem":116},{"name":"compute_incremental_hashes_map","time":0.0835,"mem":122},{"name":"load_dep_graph","time":0.235,"mem":136},{"name":"stability index","time":0.002,"mem":136},{"name":"stability checking","time":0.004,"mem":137},{"name":"type collecting","time":0.0465,"mem":146},{"name":"impl wf inference","time":0.001,"mem":146},{"name":"coherence checking","time":0.0945,"mem":154},{"name":"variance testing","time":0.0,"mem":154},{"name":"wf checking","time":0.16899999999999999,"mem":156},{"name":"item-types checking","time":0.0995,"mem":158},{"name":"item-bodies checking","time":1.3735,"mem":169},{"name":"const checking","time":0.151,"mem":173},{"name":"privacy checking","time":0.0325,"mem":173},{"name":"intrinsic checking","time":0.002,"mem":173},{"name":"effect checking","time":0.0015,"mem":173},{"name":"match checking","time":0.018000000000000003,"mem":173},{"name":"liveness checking","time":0.0125,"mem":173},{"name":"borrow checking","time":0.5175000000000001,"mem":188},{"name":"reachability checking","time":0.01,"mem":188},{"name":"death checking","time":0.006,"mem":188},{"name":"unused lib feature checking","time":0.0,"mem":188},{"name":"lint checking","time":0.1735,"mem":188},{"name":"resolving dependency formats","time":0.0,"mem":188},{"name":"translation","time":6.4415,"mem":317},{"name":"assert dep graph","time":0.0,"mem":317},{"name":"serialize dep graph","time":0.5505,"mem":317},{"name":"LLVM passes","time":19.558500000000003,"mem":341},{"name":"serialize work products","time":0.0,"mem":341},{"name":"linking","time":0.553,"mem":191}]}]},{"patch":"@040-is_valid_cap_letter","name":"regex-0.1.80","runs":[{"name":"regex-0.1.80@040-is_valid_cap_letter","passes":[{"name":"parsing","time":0.1,"mem":60},{"name":"recursion limit","time":0.0,"mem":60},{"name":"crate injection","time":0.0,"mem":60},{"name":"plugin loading","time":0.0,"mem":60},{"name":"plugin registration","time":0.0,"mem":60},{"name":"expansion","time":0.2395,"mem":101},{"name":"maybe building test harness","time":0.0,"mem":101},{"name":"maybe creating a macro crate","time":0.001,"mem":101},{"name":"checking for inline asm in case the target doesn't support it","time":0.0,"mem":101},{"name":"early lint checks","time":0.010499999999999999,"mem":101},{"name":"AST validation","time":0.001,"mem":101},{"name":"name resolution","time":0.0985,"mem":114},{"name":"complete gated feature checking","time":0.0315,"mem":114},{"name":"lowering ast -> hir","time":0.034,"mem":121},{"name":"indexing hir","time":0.0165,"mem":113},{"name":"attribute checking","time":0.001,"mem":113},{"name":"language item collection","time":0.0005,"mem":111},{"name":"lifetime resolution","time":0.003,"mem":111},{"name":"looking for entry point","time":0.0,"mem":111},{"name":"looking for plugin registrar","time":0.0,"mem":111},{"name":"loop checking","time":0.001,"mem":111},{"name":"static item recursion checking","time":0.0,"mem":111},{"name":"compute_incremental_hashes_map","time":0.08449999999999999,"mem":118},{"name":"load_dep_graph","time":0.305,"mem":130},{"name":"stability index","time":0.002,"mem":130},{"name":"stability checking","time":0.008,"mem":131},{"name":"type collecting","time":0.052500000000000008,"mem":139},{"name":"impl wf inference","time":0.001,"mem":139},{"name":"coherence checking","time":0.098,"mem":144},{"name":"variance testing","time":0.0,"mem":144},{"name":"wf checking","time":0.1765,"mem":147},{"name":"item-types checking","time":0.1075,"mem":149},{"name":"item-bodies checking","time":1.4155,"mem":162},{"name":"const checking","time":0.1615,"mem":165},{"name":"privacy checking","time":0.028999999999999999,"mem":165},{"name":"intrinsic checking","time":0.002,"mem":165},{"name":"effect checking","time":0.002,"mem":165},{"name":"match checking","time":0.018000000000000003,"mem":165},{"name":"liveness checking","time":0.004,"mem":165},{"name":"borrow checking","time":0.5335000000000001,"mem":181},{"name":"reachability checking","time":0.002,"mem":181},{"name":"death checking","time":0.01,"mem":181},{"name":"unused lib feature checking","time":0.0,"mem":181},{"name":"lint checking","time":0.1725,"mem":181},{"name":"resolving dependency formats","time":0.0,"mem":181},{"name":"translation","time":6.837,"mem":310},{"name":"assert dep graph","time":0.0,"mem":310},{"name":"serialize dep graph","time":0.6225,"mem":316},{"name":"LLVM passes","time":19.723,"mem":337},{"name":"serialize work products","time":0.0,"mem":337},{"name":"linking","time":0.551,"mem":188}]}]},{"patch":"@050-expand","name":"regex-0.1.80","runs":[{"name":"regex-0.1.80@050-expand","passes":[{"name":"parsing","time":0.1045,"mem":61},{"name":"recursion limit","time":0.0,"mem":61},{"name":"crate injection","time":0.0,"mem":61},{"name":"plugin loading","time":0.0,"mem":61},{"name":"plugin registration","time":0.0,"mem":61},{"name":"expansion","time":0.2535,"mem":101},{"name":"maybe building test harness","time":0.0,"mem":101},{"name":"maybe creating a macro crate","time":0.001,"mem":101},{"name":"checking for inline asm in case the target doesn't support it","time":0.0,"mem":101},{"name":"early lint checks","time":0.006,"mem":101},{"name":"AST validation","time":0.005,"mem":101},{"name":"name resolution","time":0.0925,"mem":115},{"name":"complete gated feature checking","time":0.033,"mem":115},{"name":"lowering ast -> hir","time":0.042499999999999999,"mem":122},{"name":"indexing hir","time":0.004,"mem":114},{"name":"attribute checking","time":0.001,"mem":114},{"name":"language item collection","time":0.004,"mem":112},{"name":"lifetime resolution","time":0.009,"mem":112},{"name":"looking for entry point","time":0.0,"mem":112},{"name":"looking for plugin registrar","time":0.0,"mem":112},{"name":"loop checking","time":0.001,"mem":112},{"name":"static item recursion checking","time":0.0,"mem":112},{"name":"compute_incremental_hashes_map","time":0.079,"mem":119},{"name":"load_dep_graph","time":0.301,"mem":131},{"name":"stability index","time":0.006,"mem":131},{"name":"stability checking","time":0.008,"mem":132},{"name":"type collecting","time":0.042499999999999999,"mem":141},{"name":"impl wf inference","time":0.001,"mem":141},{"name":"coherence checking","time":0.0975,"mem":146},{"name":"variance testing","time":0.0,"mem":146},{"name":"wf checking","time":0.174,"mem":148},{"name":"item-types checking","time":0.105,"mem":151},{"name":"item-bodies checking","time":1.374,"mem":163},{"name":"const checking","time":0.157,"mem":166},{"name":"privacy checking","time":0.033,"mem":166},{"name":"intrinsic checking","time":0.0014999999999999997,"mem":166},{"name":"effect checking","time":0.006,"mem":166},{"name":"match checking","time":0.0115,"mem":166},{"name":"liveness checking","time":0.004,"mem":166},{"name":"borrow checking","time":0.5335000000000001,"mem":182},{"name":"reachability checking","time":0.006,"mem":182},{"name":"death checking","time":0.01,"mem":182},{"name":"unused lib feature checking","time":0.0,"mem":182},{"name":"lint checking","time":0.1675,"mem":182},{"name":"resolving dependency formats","time":0.0,"mem":182},{"name":"translation","time":6.800000000000001,"mem":311},{"name":"assert dep graph","time":0.0,"mem":311},{"name":"serialize dep graph","time":0.5800000000000001,"mem":310},{"name":"LLVM passes","time":19.6075,"mem":337},{"name":"serialize work products","time":0.0,"mem":337},{"name":"linking","time":0.5495000000000001,"mem":188}]}]},{"patch":"@060-Compiler-new","name":"regex-0.1.80","runs":[{"name":"regex-0.1.80@060-Compiler-new","passes":[{"name":"parsing","time":0.10550000000000001,"mem":60},{"name":"recursion limit","time":0.0,"mem":61},{"name":"crate injection","time":0.0,"mem":61},{"name":"plugin loading","time":0.0,"mem":61},{"name":"plugin registration","time":0.0,"mem":61},{"name":"expansion","time":0.2385,"mem":101},{"name":"maybe building test harness","time":0.0,"mem":101},{"name":"maybe creating a macro crate","time":0.001,"mem":101},{"name":"checking for inline asm in case the target doesn't support it","time":0.0,"mem":101},{"name":"early lint checks","time":0.018,"mem":101},{"name":"AST validation","time":0.001,"mem":101},{"name":"name resolution","time":0.092,"mem":115},{"name":"complete gated feature checking","time":0.0295,"mem":115},{"name":"lowering ast -> hir","time":0.036000000000000007,"mem":121},{"name":"indexing hir","time":0.0045000000000000009,"mem":114},{"name":"attribute checking","time":0.005000000000000001,"mem":114},{"name":"language item collection","time":0.0005,"mem":112},{"name":"lifetime resolution","time":0.0135,"mem":112},{"name":"looking for entry point","time":0.0,"mem":112},{"name":"looking for plugin registrar","time":0.0,"mem":112},{"name":"loop checking","time":0.001,"mem":112},{"name":"static item recursion checking","time":0.0,"mem":112},{"name":"compute_incremental_hashes_map","time":0.0945,"mem":118},{"name":"load_dep_graph","time":0.257,"mem":131},{"name":"stability index","time":0.002,"mem":131},{"name":"stability checking","time":0.01,"mem":132},{"name":"type collecting","time":0.038000000000000009,"mem":140},{"name":"impl wf inference","time":0.001,"mem":141},{"name":"coherence checking","time":0.098,"mem":148},{"name":"variance testing","time":0.0,"mem":148},{"name":"wf checking","time":0.167,"mem":151},{"name":"item-types checking","time":0.0995,"mem":153},{"name":"item-bodies checking","time":1.392,"mem":163},{"name":"const checking","time":0.153,"mem":166},{"name":"privacy checking","time":0.0285,"mem":166},{"name":"intrinsic checking","time":0.006,"mem":166},{"name":"effect checking","time":0.006,"mem":166},{"name":"match checking","time":0.012,"mem":166},{"name":"liveness checking","time":0.0085,"mem":166},{"name":"borrow checking","time":0.5385,"mem":184},{"name":"reachability checking","time":0.002,"mem":184},{"name":"death checking","time":0.016,"mem":184},{"name":"unused lib feature checking","time":0.0,"mem":184},{"name":"lint checking","time":0.163,"mem":184},{"name":"resolving dependency formats","time":0.0,"mem":184},{"name":"translation","time":6.5715,"mem":311},{"name":"assert dep graph","time":0.0,"mem":311},{"name":"serialize dep graph","time":0.544,"mem":317},{"name":"LLVM passes","time":20.1255,"mem":340},{"name":"serialize work products","time":0.0,"mem":340},{"name":"linking","time":0.5515000000000001,"mem":187}]}]},{"patch":"@070-BYTE_FREQUENCIES","name":"regex-0.1.80","runs":[{"name":"regex-0.1.80@070-BYTE_FREQUENCIES","passes":[{"name":"parsing","time":0.109,"mem":60},{"name":"recursion limit","time":0.0,"mem":60},{"name":"crate injection","time":0.0,"mem":60},{"name":"plugin loading","time":0.0,"mem":60},{"name":"plugin registration","time":0.0,"mem":60},{"name":"expansion","time":0.243,"mem":101},{"name":"maybe building test harness","time":0.0,"mem":101},{"name":"maybe creating a macro crate","time":0.001,"mem":101},{"name":"checking for inline asm in case the target doesn't support it","time":0.0,"mem":101},{"name":"early lint checks","time":0.014499999999999999,"mem":101},{"name":"AST validation","time":0.001,"mem":101},{"name":"name resolution","time":0.0945,"mem":114},{"name":"complete gated feature checking","time":0.028999999999999999,"mem":114},{"name":"lowering ast -> hir","time":0.0335,"mem":121},{"name":"indexing hir","time":0.009000000000000001,"mem":114},{"name":"attribute checking","time":0.001,"mem":114},{"name":"language item collection","time":0.0,"mem":111},{"name":"lifetime resolution","time":0.009,"mem":111},{"name":"looking for entry point","time":0.0,"mem":111},{"name":"looking for plugin registrar","time":0.0,"mem":111},{"name":"loop checking","time":0.001,"mem":111},{"name":"static item recursion checking","time":0.0,"mem":111},{"name":"compute_incremental_hashes_map","time":0.0905,"mem":118},{"name":"load_dep_graph","time":0.40700000000000005,"mem":133},{"name":"stability index","time":0.008,"mem":133},{"name":"stability checking","time":0.004,"mem":133},{"name":"type collecting","time":0.048,"mem":137},{"name":"impl wf inference","time":0.0055,"mem":138},{"name":"coherence checking","time":0.0995,"mem":146},{"name":"variance testing","time":0.0,"mem":146},{"name":"wf checking","time":0.176,"mem":149},{"name":"item-types checking","time":0.108,"mem":152},{"name":"item-bodies checking","time":1.423,"mem":166},{"name":"const checking","time":0.158,"mem":169},{"name":"privacy checking","time":0.0305,"mem":169},{"name":"intrinsic checking","time":0.002,"mem":169},{"name":"effect checking","time":0.002,"mem":169},{"name":"match checking","time":0.016,"mem":169},{"name":"liveness checking","time":0.012,"mem":169},{"name":"borrow checking","time":0.5145,"mem":179},{"name":"reachability checking","time":0.002,"mem":179},{"name":"death checking","time":0.010499999999999999,"mem":180},{"name":"unused lib feature checking","time":0.0,"mem":180},{"name":"lint checking","time":0.17099999999999999,"mem":180},{"name":"resolving dependency formats","time":0.0,"mem":180},{"name":"translation","time":1.267,"mem":214},{"name":"assert dep graph","time":0.0,"mem":214},{"name":"serialize dep graph","time":0.41400000000000006,"mem":219},{"name":"LLVM passes","time":0.3,"mem":180},{"name":"serialize work products","time":0.0,"mem":180},{"name":"linking","time":0.552,"mem":178}]}]},{"patch":"@080-SparseSet","name":"regex-0.1.80","runs":[{"name":"regex-0.1.80@080-SparseSet","passes":[{"name":"parsing","time":0.101,"mem":60},{"name":"recursion limit","time":0.0,"mem":61},{"name":"crate injection","time":0.0,"mem":61},{"name":"plugin loading","time":0.0,"mem":61},{"name":"plugin registration","time":0.0,"mem":61},{"name":"expansion","time":0.2435,"mem":101},{"name":"maybe building test harness","time":0.0,"mem":101},{"name":"maybe creating a macro crate","time":0.001,"mem":101},{"name":"checking for inline asm in case the target doesn't support it","time":0.0,"mem":101},{"name":"early lint checks","time":0.014,"mem":101},{"name":"AST validation","time":0.001,"mem":101},{"name":"name resolution","time":0.097,"mem":114},{"name":"complete gated feature checking","time":0.025500000000000003,"mem":114},{"name":"lowering ast -> hir","time":0.038,"mem":121},{"name":"indexing hir","time":0.0085,"mem":113},{"name":"attribute checking","time":0.001,"mem":113},{"name":"language item collection","time":0.0,"mem":111},{"name":"lifetime resolution","time":0.007,"mem":111},{"name":"looking for entry point","time":0.0,"mem":111},{"name":"looking for plugin registrar","time":0.0,"mem":111},{"name":"loop checking","time":0.001,"mem":111},{"name":"static item recursion checking","time":0.0,"mem":111},{"name":"compute_incremental_hashes_map","time":0.08399999999999999,"mem":118},{"name":"load_dep_graph","time":0.21400000000000003,"mem":129},{"name":"stability index","time":0.002,"mem":129},{"name":"stability checking","time":0.012,"mem":130},{"name":"type collecting","time":0.04,"mem":138},{"name":"impl wf inference","time":0.001,"mem":138},{"name":"coherence checking","time":0.0935,"mem":146},{"name":"variance testing","time":0.0,"mem":146},{"name":"wf checking","time":0.168,"mem":149},{"name":"item-types checking","time":0.10300000000000001,"mem":150},{"name":"item-bodies checking","time":1.3715000000000002,"mem":161},{"name":"const checking","time":0.153,"mem":165},{"name":"privacy checking","time":0.0305,"mem":165},{"name":"intrinsic checking","time":0.002,"mem":165},{"name":"effect checking","time":0.006,"mem":165},{"name":"match checking","time":0.014,"mem":165},{"name":"liveness checking","time":0.0085,"mem":165},{"name":"borrow checking","time":0.5235000000000001,"mem":183},{"name":"reachability checking","time":0.006,"mem":183},{"name":"death checking","time":0.0185,"mem":183},{"name":"unused lib feature checking","time":0.0,"mem":183},{"name":"lint checking","time":0.1685,"mem":183},{"name":"resolving dependency formats","time":0.0,"mem":183},{"name":"translation","time":6.6985,"mem":310},{"name":"assert dep graph","time":0.0,"mem":310},{"name":"serialize dep graph","time":0.5425,"mem":330},{"name":"LLVM passes","time":20.1935,"mem":338},{"name":"serialize work products","time":0.0,"mem":338},{"name":"linking","time":0.5545,"mem":188}]}]},{"patch":"@090-Job","name":"regex-0.1.80","runs":[{"name":"regex-0.1.80@090-Job","passes":[{"name":"parsing","time":0.11,"mem":60},{"name":"recursion limit","time":0.0,"mem":60},{"name":"crate injection","time":0.0,"mem":60},{"name":"plugin loading","time":0.0,"mem":60},{"name":"plugin registration","time":0.0,"mem":60},{"name":"expansion","time":0.2535,"mem":101},{"name":"maybe building test harness","time":0.0,"mem":101},{"name":"maybe creating a macro crate","time":0.001,"mem":101},{"name":"checking for inline asm in case the target doesn't support it","time":0.0,"mem":101},{"name":"early lint checks","time":0.01,"mem":101},{"name":"AST validation","time":0.001,"mem":101},{"name":"name resolution","time":0.098,"mem":115},{"name":"complete gated feature checking","time":0.0285,"mem":115},{"name":"lowering ast -> hir","time":0.039,"mem":121},{"name":"indexing hir","time":0.013,"mem":114},{"name":"attribute checking","time":0.001,"mem":114},{"name":"language item collection","time":0.0,"mem":112},{"name":"lifetime resolution","time":0.007500000000000001,"mem":112},{"name":"looking for entry point","time":0.0,"mem":112},{"name":"looking for plugin registrar","time":0.0,"mem":112},{"name":"loop checking","time":0.001,"mem":112},{"name":"static item recursion checking","time":0.0,"mem":112},{"name":"compute_incremental_hashes_map","time":0.085,"mem":118},{"name":"load_dep_graph","time":0.28300000000000005,"mem":131},{"name":"stability index","time":0.002,"mem":131},{"name":"stability checking","time":0.008,"mem":131},{"name":"type collecting","time":0.05,"mem":140},{"name":"impl wf inference","time":0.0009999999999999996,"mem":140},{"name":"coherence checking","time":0.10500000000000001,"mem":145},{"name":"variance testing","time":0.0,"mem":145},{"name":"wf checking","time":0.1645,"mem":148},{"name":"item-types checking","time":0.1115,"mem":150},{"name":"item-bodies checking","time":1.3984999999999999,"mem":162},{"name":"const checking","time":0.1505,"mem":166},{"name":"privacy checking","time":0.0305,"mem":166},{"name":"intrinsic checking","time":0.002,"mem":166},{"name":"effect checking","time":0.004,"mem":166},{"name":"match checking","time":0.018000000000000003,"mem":166},{"name":"liveness checking","time":0.0085,"mem":166},{"name":"borrow checking","time":0.5255000000000001,"mem":182},{"name":"reachability checking","time":0.006,"mem":182},{"name":"death checking","time":0.012,"mem":182},{"name":"unused lib feature checking","time":0.0,"mem":182},{"name":"lint checking","time":0.163,"mem":182},{"name":"resolving dependency formats","time":0.0,"mem":182},{"name":"translation","time":6.6315,"mem":311},{"name":"assert dep graph","time":0.0,"mem":311},{"name":"serialize dep graph","time":0.544,"mem":317},{"name":"LLVM passes","time":19.685499999999999,"mem":334},{"name":"serialize work products","time":0.0,"mem":334},{"name":"linking","time":0.5525,"mem":188}]}]},{"patch":"@100-incr-no-change","name":"regex-0.1.80","runs":[{"name":"regex-0.1.80@100-incr-no-change","passes":[{"name":"parsing","time":0.10450000000000001,"mem":60},{"name":"recursion limit","time":0.0,"mem":61},{"name":"crate injection","time":0.0,"mem":61},{"name":"plugin loading","time":0.0,"mem":61},{"name":"plugin registration","time":0.0,"mem":61},{"name":"expansion","time":0.2445,"mem":101},{"name":"maybe building test harness","time":0.0,"mem":101},{"name":"maybe creating a macro crate","time":0.007000000000000001,"mem":101},{"name":"checking for inline asm in case the target doesn't support it","time":0.0,"mem":101},{"name":"early lint checks","time":0.010499999999999999,"mem":101},{"name":"AST validation","time":0.001,"mem":101},{"name":"name resolution","time":0.09,"mem":115},{"name":"complete gated feature checking","time":0.0325,"mem":115},{"name":"lowering ast -> hir","time":0.038,"mem":121},{"name":"indexing hir","time":0.009000000000000001,"mem":114},{"name":"attribute checking","time":0.001,"mem":114},{"name":"language item collection","time":0.0,"mem":112},{"name":"lifetime resolution","time":0.013,"mem":112},{"name":"looking for entry point","time":0.0,"mem":112},{"name":"looking for plugin registrar","time":0.0,"mem":112},{"name":"loop checking","time":0.001,"mem":112},{"name":"static item recursion checking","time":0.0,"mem":112},{"name":"compute_incremental_hashes_map","time":0.089,"mem":118},{"name":"load_dep_graph","time":0.39449999999999998,"mem":134},{"name":"stability index","time":0.002,"mem":134},{"name":"stability checking","time":0.01,"mem":135},{"name":"type collecting","time":0.0455,"mem":139},{"name":"impl wf inference","time":0.001,"mem":139},{"name":"coherence checking","time":0.095,"mem":148},{"name":"variance testing","time":0.0,"mem":148},{"name":"wf checking","time":0.17149999999999999,"mem":151},{"name":"item-types checking","time":0.108,"mem":153},{"name":"item-bodies checking","time":1.4184999999999999,"mem":167},{"name":"const checking","time":0.157,"mem":170},{"name":"privacy checking","time":0.031,"mem":170},{"name":"intrinsic checking","time":0.006,"mem":170},{"name":"effect checking","time":0.002,"mem":170},{"name":"match checking","time":0.018000000000000003,"mem":170},{"name":"liveness checking","time":0.0045000000000000009,"mem":170},{"name":"borrow checking","time":0.5325,"mem":180},{"name":"reachability checking","time":0.002,"mem":180},{"name":"death checking","time":0.015,"mem":180},{"name":"unused lib feature checking","time":0.0,"mem":180},{"name":"lint checking","time":0.172,"mem":180},{"name":"resolving dependency formats","time":0.0,"mem":180},{"name":"translation","time":1.137,"mem":210},{"name":"assert dep graph","time":0.0,"mem":210},{"name":"serialize dep graph","time":0.4075,"mem":216},{"name":"LLVM passes","time":0.0225,"mem":171},{"name":"serialize work products","time":0.0,"mem":171},{"name":"linking","time":0.5475000000000001,"mem":171}]}]}],"futures-rs-test-all":[{"patch":"","name":"futures-rs-test-all","runs":[{"name":"futures-rs-test-all","passes":[{"name":"parsing","time":0.008,"mem":53},{"name":"recursion limit","time":0.0,"mem":53},{"name":"crate injection","time":0.0,"mem":53},{"name":"plugin loading","time":0.0,"mem":53},{"name":"plugin registration","time":0.0,"mem":53},{"name":"expansion","time":0.107,"mem":83},{"name":"maybe building test harness","time":0.002,"mem":87},{"name":"maybe creating a macro crate","time":0.0,"mem":87},{"name":"checking for inline asm in case the target doesn't support it","time":0.0,"mem":87},{"name":"early lint checks","time":0.001,"mem":87},{"name":"AST validation","time":0.0,"mem":87},{"name":"name resolution","time":0.018000000000000003,"mem":93},{"name":"complete gated feature checking","time":0.0,"mem":93},{"name":"lowering ast -> hir","time":0.006,"mem":95},{"name":"indexing hir","time":0.0005,"mem":93},{"name":"attribute checking","time":0.0,"mem":93},{"name":"language item collection","time":0.0,"mem":93},{"name":"lifetime resolution","time":0.0,"mem":93},{"name":"looking for entry point","time":0.0,"mem":93},{"name":"looking for plugin registrar","time":0.0,"mem":93},{"name":"loop checking","time":0.0,"mem":93},{"name":"static item recursion checking","time":0.0,"mem":93},{"name":"compute_incremental_hashes_map","time":0.004,"mem":94},{"name":"load_dep_graph","time":0.0,"mem":94},{"name":"stability index","time":0.0,"mem":94},{"name":"stability checking","time":0.0,"mem":94},{"name":"type collecting","time":0.013,"mem":103},{"name":"impl wf inference","time":0.0,"mem":103},{"name":"coherence checking","time":0.0,"mem":103},{"name":"variance testing","time":0.0,"mem":103},{"name":"wf checking","time":0.0455,"mem":114},{"name":"item-types checking","time":0.01,"mem":114},{"name":"item-bodies checking","time":0.422,"mem":121},{"name":"const checking","time":0.026,"mem":121},{"name":"privacy checking","time":0.001,"mem":121},{"name":"intrinsic checking","time":0.0,"mem":121},{"name":"effect checking","time":0.0,"mem":121},{"name":"match checking","time":0.001,"mem":121},{"name":"liveness checking","time":0.007,"mem":121},{"name":"borrow checking","time":0.077,"mem":121},{"name":"reachability checking","time":0.0,"mem":121},{"name":"death checking","time":0.0,"mem":121},{"name":"unused lib feature checking","time":0.0,"mem":121},{"name":"lint checking","time":0.017,"mem":121},{"name":"resolving dependency formats","time":0.0,"mem":121},{"name":"translation","time":4.1075,"mem":206},{"name":"assert dep graph","time":0.0,"mem":206},{"name":"serialize dep graph","time":0.0,"mem":206},{"name":"LLVM passes","time":7.649,"mem":192},{"name":"serialize work products","time":0.0,"mem":192},{"name":"linking","time":0.59,"mem":149}]}]}],"inflate-0.1.0":[{"patch":"","name":"inflate-0.1.0","runs":[{"name":"inflate-0.1.0","passes":[{"name":"parsing","time":0.005,"mem":53},{"name":"recursion limit","time":0.0,"mem":53},{"name":"crate injection","time":0.0,"mem":53},{"name":"plugin loading","time":0.0,"mem":53},{"name":"plugin registration","time":0.0,"mem":53},{"name":"expansion","time":0.317,"mem":86},{"name":"maybe building test harness","time":0.0,"mem":86},{"name":"maybe creating a macro crate","time":0.0,"mem":86},{"name":"checking for inline asm in case the target doesn't support it","time":0.0,"mem":86},{"name":"early lint checks","time":0.014,"mem":86},{"name":"AST validation","time":0.0,"mem":86},{"name":"name resolution","time":0.114,"mem":113},{"name":"complete gated feature checking","time":0.001,"mem":113},{"name":"lowering ast -> hir","time":0.018500000000000004,"mem":121},{"name":"indexing hir","time":0.009,"mem":101},{"name":"attribute checking","time":0.0005,"mem":101},{"name":"language item collection","time":0.0,"mem":98},{"name":"lifetime resolution","time":0.001,"mem":98},{"name":"looking for entry point","time":0.0,"mem":98},{"name":"looking for plugin registrar","time":0.0,"mem":98},{"name":"loop checking","time":0.0,"mem":98},{"name":"static item recursion checking","time":0.0,"mem":98},{"name":"compute_incremental_hashes_map","time":0.056999999999999998,"mem":98},{"name":"load_dep_graph","time":0.0,"mem":98},{"name":"stability index","time":0.0005,"mem":98},{"name":"stability checking","time":0.006,"mem":98},{"name":"type collecting","time":0.0085,"mem":103},{"name":"impl wf inference","time":0.0,"mem":103},{"name":"coherence checking","time":0.0235,"mem":112},{"name":"variance testing","time":0.0,"mem":112},{"name":"wf checking","time":0.010499999999999999,"mem":113},{"name":"item-types checking","time":0.009000000000000001,"mem":113},{"name":"item-bodies checking","time":5.015000000000001,"mem":124},{"name":"const checking","time":0.051000000000000007,"mem":125},{"name":"privacy checking","time":0.002,"mem":125},{"name":"intrinsic checking","time":0.001,"mem":125},{"name":"effect checking","time":0.001,"mem":125},{"name":"match checking","time":0.013,"mem":125},{"name":"liveness checking","time":0.238,"mem":125},{"name":"borrow checking","time":0.745,"mem":139},{"name":"reachability checking","time":0.0,"mem":139},{"name":"death checking","time":0.007,"mem":139},{"name":"unused lib feature checking","time":0.0,"mem":139},{"name":"lint checking","time":0.079,"mem":136},{"name":"resolving dependency formats","time":0.0,"mem":136},{"name":"translation","time":1.6465,"mem":167},{"name":"assert dep graph","time":0.0,"mem":167},{"name":"serialize dep graph","time":0.0,"mem":167},{"name":"LLVM passes","time":2.9085,"mem":151},{"name":"serialize work products","time":0.0,"mem":151},{"name":"linking","time":0.052000000000000008,"mem":138}]}]}],"hyper.0.5.0":[{"patch":"","name":"hyper.0.5.0","runs":[{"name":"hyper.0.5.0","passes":[{"name":"parsing","time":0.08349999999999999,"mem":58},{"name":"recursion limit","time":0.0,"mem":58},{"name":"crate injection","time":0.0,"mem":58},{"name":"plugin loading","time":0.0,"mem":58},{"name":"plugin registration","time":0.0,"mem":58},{"name":"expansion","time":0.3975,"mem":112},{"name":"maybe building test harness","time":0.0,"mem":112},{"name":"maybe creating a macro crate","time":0.001,"mem":112},{"name":"checking for inline asm in case the target doesn't support it","time":0.0,"mem":112},{"name":"early lint checks","time":0.017,"mem":112},{"name":"AST validation","time":0.001,"mem":112},{"name":"name resolution","time":0.138,"mem":133},{"name":"complete gated feature checking","time":0.018,"mem":133},{"name":"lowering ast -> hir","time":0.041999999999999999,"mem":144},{"name":"indexing hir","time":0.013000000000000002,"mem":125},{"name":"attribute checking","time":0.0015,"mem":125},{"name":"language item collection","time":0.0,"mem":123},{"name":"lifetime resolution","time":0.006999999999999999,"mem":123},{"name":"looking for entry point","time":0.0,"mem":123},{"name":"looking for plugin registrar","time":0.0,"mem":123},{"name":"loop checking","time":0.001,"mem":123},{"name":"static item recursion checking","time":0.0,"mem":123},{"name":"compute_incremental_hashes_map","time":0.099,"mem":125},{"name":"load_dep_graph","time":0.0,"mem":125},{"name":"stability index","time":0.0015,"mem":125},{"name":"stability checking","time":0.014,"mem":125},{"name":"type collecting","time":0.0375,"mem":132},{"name":"impl wf inference","time":0.0009999999999999996,"mem":132},{"name":"coherence checking","time":0.075,"mem":140},{"name":"variance testing","time":0.0,"mem":140},{"name":"wf checking","time":0.2255,"mem":143},{"name":"item-types checking","time":0.10350000000000001,"mem":144},{"name":"item-bodies checking","time":1.251,"mem":158},{"name":"const checking","time":0.151,"mem":164},{"name":"privacy checking","time":0.020499999999999999,"mem":164},{"name":"intrinsic checking","time":0.006,"mem":164},{"name":"effect checking","time":0.0015,"mem":164},{"name":"match checking","time":0.0245,"mem":164},{"name":"liveness checking","time":0.0045000000000000009,"mem":164},{"name":"borrow checking","time":0.4565,"mem":172},{"name":"reachability checking","time":0.0025,"mem":172},{"name":"death checking","time":0.009000000000000001,"mem":172},{"name":"unused lib feature checking","time":0.0,"mem":172},{"name":"lint checking","time":0.16799999999999999,"mem":172},{"name":"resolving dependency formats","time":0.0,"mem":172},{"name":"translation","time":4.339,"mem":279},{"name":"assert dep graph","time":0.0,"mem":279},{"name":"serialize dep graph","time":0.0,"mem":279},{"name":"LLVM passes","time":8.9575,"mem":236},{"name":"serialize work products","time":0.0,"mem":236},{"name":"linking","time":0.2305,"mem":175}]}]}]}}